{
  "title"               : "Mersin escort | Mezitli escort | Erdemli escort",
  "description"         : "",
  "image"               : "",
  "canonical"           : "https://mersinilan.com/blog/mersin-escort-mezitli-escort-erdemli-escort-ozet",
  "content"             : "<h2>Mersin escort bayan profilleri</h2>",
  "datePublished"       : "2026-02-20T09:00:00+03:00",
  "dateModified"        : "2026-04-20T18:22:00+03:00",
  "keywords"            : {},
  "inLanguage"          : "tr-TR",
  "isAccessibleForFree" : true
}